{ "compressionlevel":-1,
 "height":18,
 "infinite":false,
 "layers":[
        {
         "data":[5, 35, 35, 35, 35, 35, 9, 35, 35, 35, 35, 35, 35, 35, 35, 35, 35, 8, 0, 34, 35, 35, 35, 8,
            15, 0, 0, 0, 0, 0, 15, 0, 0, 0, 0, 0, 0, 0, 0, 0, 0, 15, 0, 0, 0, 0, 0, 15,
            15, 0, 34, 35, 8, 0, 15, 0, 34, 35, 35, 36, 0, 4, 0, 4, 0, 49, 35, 35, 35, 8, 0, 15,
            15, 0, 0, 0, 49, 35, 41, 0, 0, 0, 0, 0, 0, 15, 0, 15, 0, 15, 0, 0, 0, 15, 0, 15,
            15, 0, 4, 0, 15, 0, 0, 0, 4, 0, 34, 35, 35, 41, 0, 15, 0, 38, 35, 8, 0, 15, 0, 15,
            15, 0, 15, 0, 49, 35, 35, 35, 52, 0, 0, 0, 0, 0, 0, 15, 0, 0, 0, 15, 0, 15, 0, 15,
            49, 35, 41, 0, 15, 0, 0, 0, 15, 0, 34, 35, 35, 35, 35, 52, 0, 4, 0, 15, 0, 15, 0, 15,
            15, 0, 0, 0, 15, 0, 4, 0, 15, 0, 0, 0, 0, 0, 0, 15, 0, 15, 0, 15, 0, 15, 0, 15,
            15, 0, 34, 35, 41, 0, 15, 0, 38, 35, 35, 35, 35, 8, 0, 15, 0, 15, 0, 15, 0, 26, 0, 15,
            15, 0, 0, 0, 0, 0, 15, 0, 0, 0, 0, 0, 0, 15, 0, 15, 0, 15, 0, 15, 0, 0, 0, 15,
            49, 35, 35, 35, 8, 0, 38, 35, 35, 35, 35, 8, 0, 15, 0, 15, 0, 15, 0, 15, 0, 4, 0, 15,
            15, 0, 0, 0, 26, 0, 0, 0, 0, 0, 0, 15, 0, 26, 0, 15, 0, 15, 0, 15, 0, 15, 0, 15,
            15, 0, 4, 0, 0, 4, 0, 5, 35, 8, 0, 15, 0, 0, 0, 15, 0, 15, 0, 15, 0, 15, 0, 15,
            15, 0, 49, 36, 0, 15, 0, 26, 0, 15, 0, 49, 35, 8, 0, 26, 0, 15, 0, 15, 0, 38, 35, 52,
            15, 0, 15, 0, 0, 15, 0, 0, 0, 15, 0, 15, 0, 15, 0, 0, 0, 15, 0, 15, 0, 0, 0, 15,
            15, 0, 38, 35, 35, 42, 35, 35, 35, 41, 0, 15, 0, 38, 35, 35, 35, 41, 0, 38, 35, 36, 0, 15,
            15, 0, 0, 0, 0, 0, 0, 0, 0, 0, 0, 15, 0, 0, 0, 0, 0, 0, 0, 0, 0, 0, 0, 15,
            38, 36, 0, 34, 35, 35, 35, 35, 35, 35, 35, 42, 35, 35, 35, 35, 35, 35, 35, 35, 35, 35, 35, 41],
         "height":18,
         "id":1,
         "locked":true,
         "name":"layerWall",
         "opacity":1,
         "type":"tilelayer",
         "visible":true,
         "width":24,
         "x":0,
         "y":0
        }],
 "nextlayerid":2,
 "nextobjectid":1,
 "orientation":"orthogonal",
 "renderorder":"right-down",
 "tiledversion":"1.10.1",
 "tileheight":32,
 "tilesets":[
        {
         "columns":11,
         "firstgid":1,
         "image":"..\/wall-tiles.png",
         "imageheight":160,
         "imagewidth":352,
         "margin":0,
         "name":"TileBasic",
         "spacing":0,
         "tilecount":55,
         "tileheight":32,
         "tilewidth":32
        }],
 "tilewidth":32,
 "type":"map",
 "version":"1.10",
 "width":24
}